{
 "bbc_europe": {
  "etag": null,
  "last_modified": null,
  "fetched_at": "2026-07-13T11:27:02.713051+00:00"
 },
 "guardian_eu": {
  "etag": "W/\"hash4347600697465396852\"",
  "last_modified": null,
  "fetched_at": "2026-07-13T11:27:02.975296+00:00"
 },
 "politico_eu": {
  "etag": "\"af1aa652ce730f89fa896d2522cb86ee\"",
  "last_modified": "Mon, 13 Jul 2026 11:24:36 GMT",
  "fetched_at": "2026-07-13T11:27:03.088173+00:00"
 },
 "dw_europe": {
  "etag": null,
  "last_modified": null,
  "fetched_at": "2026-07-13T11:27:04.129240+00:00"
 },
 "el_moldova": {
  "etag": null,
  "last_modified": null,
  "fetched_at": "2026-07-13T11:27:04.819962+00:00"
 },
 "extern": {
  "etag": null,
  "last_modified": null,
  "fetched_at": "2026-07-13T11:27:07.245527+00:00"
 },
 "gsp": {
  "etag": null,
  "last_modified": null,
  "fetched_at": "2026-07-13T11:27:08.138546+00:00"
 },
 "digisport": {
  "etag": null,
  "last_modified": null,
  "fetched_at": "2026-07-13T11:27:09.671158+00:00"
 },
 "prosport": {
  "etag": "\"b7bf52472df5dd1feb482b73f15d83d5\"",
  "last_modified": "Mon, 13 Jul 2026 11:24:59 GMT",
  "fetched_at": "2026-07-13T11:27:11.786547+00:00"
 },
 "startup": {
  "etag": null,
  "last_modified": null,
  "fetched_at": "2026-07-13T11:27:13.490491+00:00"
 },
 "autocritica": {
  "etag": "\"7634314d836e32d24256aa01d9aeb262\"",
  "last_modified": "Mon, 13 Jul 2026 10:34:05 GMT",
  "fetched_at": "2026-07-13T11:27:18.510191+00:00"
 },
 "spotmedia": {
  "etag": "\"15d17742073f5dec8f4401bb1bd2fc9a\"",
  "last_modified": "Mon, 13 Jul 2026 09:45:08 GMT",
  "fetched_at": "2026-07-13T11:27:19.165405+00:00"
 },
 "digi24": {
  "etag": null,
  "last_modified": null,
  "fetched_at": "2026-07-13T11:27:21.192128+00:00"
 },
 "hotnews": {
  "etag": "\"fa64ad0f12d2aca8463e611d612c3d39\"",
  "last_modified": "Mon, 13 Jul 2026 11:25:25 GMT",
  "fetched_at": "2026-07-13T11:27:21.568001+00:00"
 },
 "g4media": {
  "etag": "\"2d9eaa1db2a48776e230d3e5f8979886\"",
  "last_modified": "Mon, 13 Jul 2026 11:26:31 GMT",
  "fetched_at": "2026-07-13T11:27:22.348169+00:00"
 },
 "recorder": {
  "etag": "W/\"b41aabdf92c5e648f553b873a89802ed\"",
  "last_modified": "Mon, 13 Jul 2026 11:17:33 GMT",
  "fetched_at": "2026-07-13T11:27:23.113277+00:00"
 },
 "contributors": {
  "etag": "W/\"d9c99c75a1423e6857c1356333509a2e\"",
  "last_modified": "Mon, 13 Jul 2026 05:29:44 GMT",
  "fetched_at": "2026-07-13T11:27:24.421286+00:00"
 },
 "tolo": {
  "etag": "\"a79f37c15efffec77ef457f4c9a4094a\"",
  "last_modified": "Sat, 20 Jun 2026 21:47:13 GMT",
  "fetched_at": "2026-07-13T11:27:25.669980+00:00"
 },
 "zf": {
  "etag": null,
  "last_modified": "Mon, 13 Jul 2026 11:27:27 GMT",
  "fetched_at": "2026-07-13T11:27:28.294046+00:00"
 },
 "economica": {
  "etag": "\"c99b0bf78f3a55e410564ad2a59ec29a\"",
  "last_modified": "Mon, 13 Jul 2026 11:26:52 GMT",
  "fetched_at": "2026-07-13T11:27:29.003307+00:00"
 },
 "economedia": {
  "etag": "\"b7615b9bea2b829b801717031ef1c33f\"",
  "last_modified": "Mon, 13 Jul 2026 11:10:48 GMT",
  "fetched_at": "2026-07-13T11:27:30.512879+00:00"
 },
 "cursdeguv": {
  "etag": null,
  "last_modified": "Mon, 13 Jul 2026 11:09:46 GMT",
  "fetched_at": "2026-07-13T11:27:30.895238+00:00"
 },
 "protv": {
  "etag": null,
  "last_modified": null,
  "fetched_at": "2026-07-13T11:27:32.282928+00:00"
 },
 "libertatea": {
  "etag": "\"8129f80056cc0c77a14cdd4042747481\"",
  "last_modified": "Sat, 11 Jul 2026 03:31:46 GMT",
  "fetched_at": "2026-07-11T03:37:06.111089+00:00"
 }
}